LICENSE
MANIFEST.in
README.md
setup.py
kernels_mixer/__init__.py
kernels_mixer/config.py
kernels_mixer/kernels.py
kernels_mixer/kernels_test.py
kernels_mixer/kernelspecs.py
kernels_mixer/websockets.py
kernels_mixer/websockets_test.py
kernels_mixer.egg-info/PKG-INFO
kernels_mixer.egg-info/SOURCES.txt
kernels_mixer.egg-info/dependency_links.txt
kernels_mixer.egg-info/requires.txt
kernels_mixer.egg-info/top_level.txt