Metadata-Version: 2.1
Name: kernels-mixer
Version: 0.0.13
Summary: Jupyter server extension that allows mixing local and remote kernels together
Home-page: https://github.com/GoogleCloudPlatform/jupyter-extensions/tree/master/kernels-mixer
Author: Google, Inc.
License: Apache License 2.0
Requires-Python: >=3.8
License-File: LICENSE
Requires-Dist: jupyter_server>=2.7.3
Requires-Dist: traitlets
Requires-Dist: google-cloud-jupyter-config
